incp/__init__.py
incp/incp.py
incp_v1-0.1.0.dist-info/METADATA
incp_v1-0.1.0.dist-info/WHEEL
incp_v1-0.1.0.dist-info/entry_points.txt
incp_v1-0.1.0.dist-info/top_level.txt
incp_v1-0.1.0.dist-info/RECORD
