Metadata-Version: 2.1
Name: incp-v1
Version: 0.1.0
Summary: Get the Employee Data and incp Data
Home-page: https://github.com/A284viral/incp_v1
Author: Aviral Srivastava
Author-email: aviralsrivastava284@gmail.com
Classifier: Programming Language :: Python :: 3
Classifier: License :: OSI Approved :: MIT License
Classifier: Operating System :: OS Independent
Requires-Python: >=3.6
Requires-Dist: pandas
